{"neurons":[{"trace":{"elegibility":{},"extended":{}},"state":0,"old":0,"activation":0.4666666666666667,"bias":0,"layer":"input","squash":"LOGISTIC"},{"trace":{"elegibility":{},"extended":{}},"state":0,"old":0,"activation":0.609704641350211,"bias":0,"layer":"input","squash":"LOGISTIC"},{"trace":{"elegibility":{},"extended":{}},"state":0,"old":0,"activation":0.17,"bias":0,"layer":"input","squash":"LOGISTIC"},{"trace":{"elegibility":{},"extended":{}},"state":-1.5541810477463631,"old":4.6554004341951,"activation":0.17448321509136022,"bias":-6.667678163259527,"layer":"0","squash":"LOGISTIC"},{"trace":{"elegibility":{},"extended":{}},"state":3.176426386271311,"old":0.49032400347850646,"activation":0.9599374593418059,"bias":5.506789344185235,"layer":"0","squash":"LOGISTIC"},{"trace":{"elegibility":{},"extended":{}},"state":2.2532012295976807,"old":0.32954387400237806,"activation":0.904926309118222,"bias":3.996942804661299,"layer":"0","squash":"LOGISTIC"},{"trace":{"elegibility":{},"extended":{}},"state":3.54114830211831,"old":0.7701364219491467,"activation":0.9718361588276051,"bias":6.174490172756182,"layer":"0","squash":"LOGISTIC"},{"trace":{"elegibility":{},"extended":{}},"state":10.525593146979773,"old":1.4225032210152881,"activation":0.9999731600735792,"bias":-2.1746044087161756,"layer":"1","squash":"LOGISTIC"},{"trace":{"elegibility":{},"extended":{}},"state":10.871228705058419,"old":1.2746140096076228,"activation":0.9999810033460441,"bias":-1.7706329196052466,"layer":"1","squash":"LOGISTIC"},{"trace":{"elegibility":{},"extended":{}},"state":4.611873655611669,"old":7.321781347761812,"activation":0.9901645083174827,"bias":-4.476038006855862,"layer":"1","squash":"LOGISTIC"},{"trace":{"elegibility":{},"extended":{}},"state":5.42828353744428,"old":0.09321344509764362,"activation":0.9956285676401683,"bias":-3.4575874931631074,"layer":"1","squash":"LOGISTIC"},{"trace":{"elegibility":{},"extended":{}},"state":0.9298173392012146,"old":7.679182303794973,"activation":0.7170382261075628,"bias":13.933604301864964,"layer":"output","squash":"LOGISTIC"},{"trace":{"elegibility":{},"extended":{}},"state":7.016080197471657,"old":4.566908518642103,"activation":0.9991034685019728,"bias":-5.733770818134305,"layer":"output","squash":"LOGISTIC"}],"connections":[{"from":"0","to":"3","weight":-1.384784739155793,"gater":null},{"from":"0","to":"4","weight":-6.377354594147887,"gater":null},{"from":"0","to":"5","weight":-5.086000099449687,"gater":null},{"from":"0","to":"6","weight":-8.330924785982043,"gater":null},{"from":"1","to":"3","weight":8.264588954550984,"gater":null},{"from":"1","to":"4","weight":0.15279720782631326,"gater":null},{"from":"1","to":"5","weight":0.34292517998050603,"gater":null},{"from":"1","to":"6","weight":0.9609159716496627,"gater":null},{"from":"2","to":"3","weight":4.238404805682448,"gater":null},{"from":"2","to":"4","weight":3.2503573322789805,"gater":null},{"from":"2","to":"5","weight":2.4742775469007,"gater":null},{"from":"2","to":"6","weight":3.9324971941664137,"gater":null},{"from":"3","to":"7","weight":-5.5823131364711065,"gater":null},{"from":"3","to":"8","weight":-6.15853652518936,"gater":null},{"from":"3","to":"9","weight":6.460670602211845,"gater":null},{"from":"3","to":"10","weight":-2.747010773247678,"gater":null},{"from":"4","to":"7","weight":5.070219314185268,"gater":null},{"from":"4","to":"8","weight":5.196433752213871,"gater":null},{"from":"4","to":"9","weight":2.2784024229490902,"gater":null},{"from":"4","to":"10","weight":3.044544219387864,"gater":null},{"from":"5","to":"7","weight":3.855371487405343,"gater":null},{"from":"5","to":"8","weight":3.9229081071097816,"gater":null},{"from":"5","to":"9","weight":1.3844272965594504,"gater":null},{"from":"5","to":"10","weight":2.677514333204549,"gater":null},{"from":"6","to":"7","weight":5.472422568735752,"gater":null},{"from":"6","to":"8","weight":5.328294827771886,"gater":null},{"from":"6","to":"9","weight":4.6511565118779,"gater":null},{"from":"6","to":"10","weight":4.136275757571272,"gater":null},{"from":"7","to":"11","weight":-8.897800161466957,"gater":null},{"from":"7","to":"12","weight":2.9115083564500357,"gater":null},{"from":"8","to":"11","weight":-9.364767623825369,"gater":null},{"from":"8","to":"12","weight":2.250111512191216,"gater":null},{"from":"9","to":"11","weight":11.416006273038978,"gater":null},{"from":"9","to":"12","weight":4.610355395572214,"gater":null},{"from":"10","to":"11","weight":-6.078464805021889,"gater":null},{"from":"10","to":"12","weight":3.036625068297654,"gater":null}]}